d3rlpy/__init__.py
d3rlpy/_version.py
d3rlpy/base.py
d3rlpy/cli.py
d3rlpy/constants.py
d3rlpy/dataclass_utils.py
d3rlpy/datasets.py
d3rlpy/distributed.py
d3rlpy/healthcheck.py
d3rlpy/interface.py
d3rlpy/itertools.py
d3rlpy/notebook_utils.py
d3rlpy/serializable_config.py
d3rlpy/torch_utility.py
d3rlpy/types.py
d3rlpy/algos/__init__.py
d3rlpy/algos/utility.py
d3rlpy/algos/qlearning/__init__.py
d3rlpy/algos/qlearning/awac.py
d3rlpy/algos/qlearning/base.py
d3rlpy/algos/qlearning/bc.py
d3rlpy/algos/qlearning/bcq.py
d3rlpy/algos/qlearning/bear.py
d3rlpy/algos/qlearning/cal_ql.py
d3rlpy/algos/qlearning/cql.py
d3rlpy/algos/qlearning/crr.py
d3rlpy/algos/qlearning/ddpg.py
d3rlpy/algos/qlearning/dqn.py
d3rlpy/algos/qlearning/explorers.py
d3rlpy/algos/qlearning/iql.py
d3rlpy/algos/qlearning/nfq.py
d3rlpy/algos/qlearning/plas.py
d3rlpy/algos/qlearning/prdc.py
d3rlpy/algos/qlearning/random_policy.py
d3rlpy/algos/qlearning/rebrac.py
d3rlpy/algos/qlearning/sac.py
d3rlpy/algos/qlearning/td3.py
d3rlpy/algos/qlearning/td3_plus_bc.py
d3rlpy/algos/qlearning/torch/__init__.py
d3rlpy/algos/qlearning/torch/awac_impl.py
d3rlpy/algos/qlearning/torch/bc_impl.py
d3rlpy/algos/qlearning/torch/bcq_impl.py
d3rlpy/algos/qlearning/torch/bear_impl.py
d3rlpy/algos/qlearning/torch/cal_ql_impl.py
d3rlpy/algos/qlearning/torch/cql_impl.py
d3rlpy/algos/qlearning/torch/crr_impl.py
d3rlpy/algos/qlearning/torch/ddpg_impl.py
d3rlpy/algos/qlearning/torch/dqn_impl.py
d3rlpy/algos/qlearning/torch/iql_impl.py
d3rlpy/algos/qlearning/torch/plas_impl.py
d3rlpy/algos/qlearning/torch/prdc_impl.py
d3rlpy/algos/qlearning/torch/rebrac_impl.py
d3rlpy/algos/qlearning/torch/sac_impl.py
d3rlpy/algos/qlearning/torch/td3_impl.py
d3rlpy/algos/qlearning/torch/td3_plus_bc_impl.py
d3rlpy/algos/qlearning/torch/utility.py
d3rlpy/algos/transformer/__init__.py
d3rlpy/algos/transformer/action_samplers.py
d3rlpy/algos/transformer/base.py
d3rlpy/algos/transformer/decision_transformer.py
d3rlpy/algos/transformer/inputs.py
d3rlpy-2.8.1.dist-info/LICENSE
d3rlpy-2.8.1.dist-info/METADATA
d3rlpy-2.8.1.dist-info/WHEEL
d3rlpy-2.8.1.dist-info/entry_points.txt
d3rlpy-2.8.1.dist-info/top_level.txt
d3rlpy-2.8.1.dist-info/zip-safe
d3rlpy-2.8.1.dist-info/RECORD
