Metadata-Version: 2.1
Name: d3rlpy
Version: 2.8.1
Summary: An offline deep reinforcement learning library
Home-page: https://github.com/takuseno/d3rlpy
Author: Takuma Seno
Author-email: takuma.seno@gmail.com
License: MIT License
Platform: UNKNOWN
Classifier: Development Status :: 5 - Production/Stable
Classifier: Intended Audience :: Developers
Classifier: Intended Audience :: Education
Classifier: Intended Audience :: Science/Research
Classifier: Topic :: Scientific/Engineering
Classifier: Topic :: Scientific/Engineering :: Artificial Intelligence
Classifier: Programming Language :: Python :: 3.9
Classifier: Programming Language :: Python :: 3.10
Classifier: Programming Language :: Python :: 3.11
Classifier: Programming Language :: Python :: Implementation :: CPython
Classifier: Operating System :: POSIX :: Linux
Classifier: Operating System :: Microsoft :: Windows
Classifier: Operating System :: MacOS :: MacOS X
Requires-Python: >=3.9.0
Requires-Dist: torch >=2.5.0
Requires-Dist: tqdm >=4.66.3
Requires-Dist: h5py
Requires-Dist: gym >=0.26.0
Requires-Dist: click
Requires-Dist: typing-extensions
Requires-Dist: structlog
Requires-Dist: colorama
Requires-Dist: dataclasses-json
Requires-Dist: gymnasium ==1.0.0
Requires-Dist: scikit-learn
